elf/__init__.py
elf/_version.py
elf/answer.py
elf/aoc_client.py
elf/cache.py
elf/cli.py
elf/client.py
elf/constants.py
elf/exceptions.py
elf/guesses.py
elf/helpers.py
elf/input.py
elf/leaderboard.py
elf/messages.py
elf/models.py
elf/open.py
elf/py.typed
elf/status.py
elf/utils.py
elf-1.1.1.dist-info/licenses/LICENSE
elf-1.1.1.dist-info/METADATA
elf-1.1.1.dist-info/WHEEL
elf-1.1.1.dist-info/entry_points.txt
elf-1.1.1.dist-info/top_level.txt
elf-1.1.1.dist-info/RECORD
