Metadata-Version: 2.4
Name: elf
Version: 1.1.1
Summary: Advent of Code helper for Python: fetch and cache inputs, submit answers, and pull private leaderboards.
Author-email: cak <cak@typeerror.com>
License-Expression: MIT
Project-URL: Homepage, https://github.com/cak/elf
Project-URL: Documentation, https://github.com/cak/elf/
Project-URL: Repository, https://github.com/cak/elf
Project-URL: Issue-Tracker, https://github.com/cak/elf/issues
Keywords: advent of code,aoc,cli,python,puzzles
Classifier: Intended Audience :: Developers
Classifier: Programming Language :: Python :: 3 :: Only
Classifier: Programming Language :: Python :: 3.11
Classifier: Programming Language :: Python :: 3.12
Classifier: Programming Language :: Python :: 3.13
Classifier: Programming Language :: Python :: 3.14
Classifier: Topic :: Games/Entertainment :: Puzzle Games
Classifier: Topic :: Software Development :: Libraries
Classifier: Topic :: Utilities
Classifier: Typing :: Typed
Requires-Python: >=3.11
License-File: LICENSE
Requires-Dist: beautifulsoup4>=4.14.2
Requires-Dist: httpx>=0.28.1
Requires-Dist: pydantic>=2.12.4
Requires-Dist: rich>=14.2.0
Requires-Dist: typer>=0.20.0
Dynamic: license-file
